cytoself/__init__.py
cytoself/analysis/__init__.py
cytoself/analysis/analytics.py
cytoself/analysis/pearson_correlation.py
cytoself/analysis/plot_functions/__init__.py
cytoself/analysis/plot_functions/batch2grid.py
cytoself/analysis/plot_functions/plot_histories.py
cytoself/analysis/plot_functions/plot_reconstruction_panel.py
cytoself/components/__init__.py
cytoself/components/blocks/__init__.py
cytoself/components/blocks/conv_block.py
cytoself/components/blocks/fc_block.py
cytoself/components/decoders/__init__.py
cytoself/components/decoders/resnet.py
cytoself/components/layers/__init__.py
cytoself/components/layers/activation.py
cytoself/components/layers/histcounts.py
cytoself/components/layers/loss.py
cytoself/components/layers/norm_mse.py
cytoself/components/layers/upconcat.py
cytoself/components/metrics/__init__.py
cytoself/components/metrics/metric.py
cytoself/components/utils/__init__.py
cytoself/components/utils/history_utils.py
cytoself/data_loader/__init__.py
cytoself/data_loader/data_generator.py
cytoself/data_loader/data_manager.py
cytoself/external/__init__.py
cytoself/external/callbacks.py
cytoself/external/efficientnet2d.py
cytoself/external/layers/__init__.py
cytoself/external/layers/vq.py
cytoself/models/__init__.py
cytoself/models/base.py
cytoself/models/full.py
cytoself/models/pretext.py
cytoself/models/splitq.py
cytoself/utils/__init__.py
cytoself/utils/path_utils.py
cytoself-0.0.1.4.dist-info/LICENSE.txt
cytoself-0.0.1.4.dist-info/METADATA
cytoself-0.0.1.4.dist-info/WHEEL
cytoself-0.0.1.4.dist-info/top_level.txt
cytoself-0.0.1.4.dist-info/RECORD
