Metadata-Version: 2.1
Name: cytoself
Version: 0.0.1.4
Summary: An image feature extractor with self-supervised learning
Home-page: https://github.com/royerlab/cytoself
Author: 
Author-email: 
License: BSD 3-Clause
Project-URL: Bug Tracker, https://github.com/royerlab/cytoself/issues
Classifier: Programming Language :: Python :: 3 :: Only
Classifier: Programming Language :: Python :: 3.7
Classifier: License :: OSI Approved :: BSD License
Classifier: Operating System :: OS Independent
Classifier: Topic :: Scientific/Engineering
Classifier: Topic :: Scientific/Engineering :: Artificial Intelligence
Classifier: Topic :: Scientific/Engineering :: Bio-Informatics
Classifier: Topic :: Scientific/Engineering :: Image Processing
Classifier: Topic :: Scientific/Engineering :: Image Recognition
Classifier: Topic :: Scientific/Engineering :: Information Analysis
Requires-Python: >=3.7, <3.8
License-File: LICENSE.txt
Requires-Dist: numpy (>=1.19)
Requires-Dist: pandas (>1.1)
Requires-Dist: joblib (==1.0.1)
Requires-Dist: tensorflow (==1.15.*)
Requires-Dist: matplotlib (==3.1.3)
Requires-Dist: umap-learn (==0.5.1)
Requires-Dist: gdown (==4.3.0)
Requires-Dist: tqdm (==4.55.1)
Requires-Dist: colorcet (==2.0.6)
Requires-Dist: seaborn (==0.10.1)
Requires-Dist: h5py (==2.10.0)
